odoo/addons/shopinvader_invoice/README.rst
odoo/addons/shopinvader_invoice/__init__.py
odoo/addons/shopinvader_invoice/__manifest__.py
odoo/addons/shopinvader_invoice/i18n/shopinvader_invoice.pot
odoo/addons/shopinvader_invoice/readme/CONTRIBUTORS.rst
odoo/addons/shopinvader_invoice/readme/DESCRIPTION.rst
odoo/addons/shopinvader_invoice/services/__init__.py
odoo/addons/shopinvader_invoice/services/invoice.py
odoo/addons/shopinvader_invoice/static/description/index.html
odoo/addons/shopinvader_invoice/tests/__init__.py
odoo/addons/shopinvader_invoice/tests/common.py
odoo/addons/shopinvader_invoice/tests/test_invoice_service.py
odoo14_addon_shopinvader_invoice-14.0.2.2.0.dist-info/METADATA
odoo14_addon_shopinvader_invoice-14.0.2.2.0.dist-info/WHEEL
odoo14_addon_shopinvader_invoice-14.0.2.2.0.dist-info/top_level.txt
odoo14_addon_shopinvader_invoice-14.0.2.2.0.dist-info/RECORD
